flask_http_middleware/__init__.py
flask_http_middleware/base.py
flask_http_middleware/manager.py
flask_http_middleware-0.4.3.dist-info/LICENSE
flask_http_middleware-0.4.3.dist-info/METADATA
flask_http_middleware-0.4.3.dist-info/WHEEL
flask_http_middleware-0.4.3.dist-info/top_level.txt
flask_http_middleware-0.4.3.dist-info/RECORD
