Metadata-Version: 2.1
Name: flask-http-middleware
Version: 0.4.3
Summary: A module to create middleware with direct access to `request` and `response`
Home-page: https://github.com/Danangjoyoo/flask-http-middleware
Author: danangjoyoo (Agus Danangjoyo)
Author-email: <agus.danangjoyo.blog@gmail.com>
Keywords: flask,middleware,http,request,response
Classifier: Development Status :: 5 - Production/Stable
Classifier: Intended Audience :: Developers
Classifier: Programming Language :: Python :: 3 :: Only
Classifier: Programming Language :: Python :: 3.7
Classifier: Programming Language :: Python :: 3.8
Classifier: Programming Language :: Python :: 3.9
Classifier: Programming Language :: Python :: 3.10
Classifier: Programming Language :: Python :: 3.11
Classifier: Environment :: Web Environment
Classifier: Operating System :: OS Independent
Classifier: Typing :: Typed
License-File: LICENSE
Requires-Dist: flask
Requires-Dist: werkzeug
